gias3.registration-3.0.2-py3.11-nspkg.pth
gias3/registration/RBF.py
gias3/registration/__init__.py
gias3/registration/alignment_analytic.py
gias3/registration/alignment_fitting.py
gias3/registration/shapemodel.py
gias3.registration-3.0.2.dist-info/LICENSE
gias3.registration-3.0.2.dist-info/METADATA
gias3.registration-3.0.2.dist-info/WHEEL
gias3.registration-3.0.2.dist-info/namespace_packages.txt
gias3.registration-3.0.2.dist-info/top_level.txt
gias3.registration-3.0.2.dist-info/RECORD
